{
  "gitSyncId": "6825da0a3c739a115ba456b7_f6a3ecef-a992-49a3-8607-3f6c579b63be",
  "id": "Page1_GetClasses",
  "pluginId": "postgres-plugin",
  "pluginType": "DB",
  "unpublishedAction": {
    "actionConfiguration": {
      "body": "SELECT DISTINCT class FROM student_data;\n",
      "encodeParamsToggle": true,
      "paginationType": "NONE",
      "pluginSpecifiedTemplates": [
        {
          "value": true
        }
      ],
      "timeoutInMillisecond": 10000
    },
    "confirmBeforeExecute": false,
    "datasource": {
      "id": "StudentDB",
      "isAutoGenerated": false,
      "name": "StudentDB",
      "pluginId": "postgres-plugin"
    },
    "dynamicBindingPathList": [],
    "executeOnLoad": true,
    "name": "GetClasses",
    "pageId": "Page1",
    "userSetOnLoad": false
  }
}